README.txt
setup.py
collective/__init__.py
collective.ptg.galleryimage.egg-info/PKG-INFO
collective.ptg.galleryimage.egg-info/SOURCES.txt
collective.ptg.galleryimage.egg-info/dependency_links.txt
collective.ptg.galleryimage.egg-info/entry_points.txt
collective.ptg.galleryimage.egg-info/namespace_packages.txt
collective.ptg.galleryimage.egg-info/not-zip-safe
collective.ptg.galleryimage.egg-info/requires.txt
collective.ptg.galleryimage.egg-info/top_level.txt
collective/ptg/__init__.py
collective/ptg/galleryimage/__init__.py
collective/ptg/galleryimage/configure.zcml
collective/ptg/galleryimage/extender.py
collective/ptg/galleryimage/tests.py
collective/ptg/galleryimage/version.txt
collective/ptg/galleryimage/profiles/default/gallerysettings.json
collective/ptg/galleryimage/profiles/default/metadata.xml
collective/ptg/galleryimage/profiles/default/propertiestool.xml
collective/ptg/galleryimage/profiles/default/types.xml
collective/ptg/galleryimage/profiles/default/types/GalleryImage.xml
docs/HISTORY.txt
docs/INSTALL.txt
docs/LICENSE.GPL
docs/LICENSE.txt